niha1999/__init__.py
niha1999/hello.py
niha19999-0.1.0.dist-info/METADATA
niha19999-0.1.0.dist-info/WHEEL
niha19999-0.1.0.dist-info/top_level.txt
niha19999-0.1.0.dist-info/RECORD
